{
    "version": "1.0",
    "migrations": [
        {
            "id": "mig_f0151b347e31",
            "sql": "CREATE TABLE \"api_tokens\" (\n  \"user_id\" TEXT NOT NULL,\n  \"name\" TEXT NOT NULL,\n  \"token_hash\" TEXT NOT NULL,\n  \"expires_at\" TEXT,\n  \"last_used_at\" TEXT,\n  \"id\" TEXT PRIMARY KEY NOT NULL,\n  \"created_at\" DATETIME DEFAULT CURRENT_TIMESTAMP,\n  \"updated_at\" DATETIME DEFAULT CURRENT_TIMESTAMP,\n  FOREIGN KEY (\"user_id\") REFERENCES \"users\" (\"id\") ON DELETE RESTRICT ON UPDATE CASCADE\n)",
            "destructive": false,
            "generated_at": "2025-09-27T14:19:23+00:00",
            "table": "api_tokens",
            "operation": "create_table",
            "warning": null
        },
        {
            "id": "mig_a684b3eb7c1c",
            "sql": "CREATE TABLE \"users\" (\n  \"name\" TEXT NOT NULL,\n  \"password\" TEXT NOT NULL,\n  \"email\" TEXT NOT NULL,\n  \"active\" INTEGER NOT NULL,\n  \"id\" TEXT PRIMARY KEY NOT NULL,\n  \"created_at\" DATETIME DEFAULT CURRENT_TIMESTAMP,\n  \"updated_at\" DATETIME DEFAULT CURRENT_TIMESTAMP\n)",
            "destructive": false,
            "generated_at": "2025-09-27T14:19:23+00:00",
            "table": "users",
            "operation": "create_table",
            "warning": null
        },
        {
            "id": "mig_bfcf39e40148",
            "sql": "CREATE UNIQUE INDEX \"uniq_api_tokens_token_hash\" ON \"api_tokens\" (\"token_hash\")",
            "destructive": false,
            "generated_at": "2025-09-27T14:19:23+00:00",
            "table": "api_tokens",
            "operation": "add_index",
            "warning": null
        },
        {
            "id": "mig_bf19555b1609",
            "sql": "CREATE INDEX \"idx_api_tokens_user_id\" ON \"api_tokens\" (\"user_id\")",
            "destructive": false,
            "generated_at": "2025-09-27T14:19:23+00:00",
            "table": "api_tokens",
            "operation": "add_index",
            "warning": null
        },
        {
            "id": "mig_471ef548fac7",
            "sql": "CREATE UNIQUE INDEX \"uniq_users_email\" ON \"users\" (\"email\")",
            "destructive": false,
            "generated_at": "2025-09-27T14:19:23+00:00",
            "table": "users",
            "operation": "add_index",
            "warning": null
        },
        {
            "id": "mig_b93b059a8555",
            "sql": "CREATE TABLE jobs (\n    id TEXT PRIMARY KEY,\n    queue TEXT NOT NULL DEFAULT 'default',\n    payload TEXT NOT NULL,\n    status TEXT NOT NULL DEFAULT 'pending' CHECK (status IN ('pending', 'processing', 'completed', 'failed')),\n    attempts INTEGER NOT NULL DEFAULT 0,\n    error TEXT,\n    run_at DATETIME NOT NULL,\n    started_at DATETIME,\n    completed_at DATETIME,\n    failed_at DATETIME,\n    created_at DATETIME NOT NULL DEFAULT CURRENT_TIMESTAMP\n);\n\n-- Create essential indexes for queue performance\nCREATE INDEX jobs_queue_status_run_at_index ON jobs (queue, status, run_at);\nCREATE INDEX jobs_status_run_at_index ON jobs (status, run_at);\nCREATE INDEX jobs_status_index ON jobs (status);",
            "destructive": false,
            "generated_at": "2025-09-27T14:19:33+00:00",
            "table": "jobs",
            "operation": "create_table",
            "description": "Create jobs table and indexes for queue system"
        }
    ]
}